HandsAnalyzer/Hand.py
HandsAnalyzer/HandsAnalyzer.py
HandsAnalyzer/__init__.py
HandsAnalyzer/helpers/__init__.py
HandsAnalyzer/helpers/estimation/__init__.py
HandsAnalyzer/helpers/estimation/kalman.py
HandsAnalyzer/helpers/geometry/__init__.py
HandsAnalyzer/helpers/geometry/euclidian.py
HandsAnalyzer/helpers/geometry/orientation.py
HandsAnalyzer/helpers/ui/__init__.py
HandsAnalyzer/helpers/ui/opencv/__init__.py
HandsAnalyzer/helpers/ui/pillow/__init__.py
HandsAnalyzer/helpers/ui/pygame/__init__.py
HandsAnalyzer/helpers/ui/pygame/colors.py
HandsAnalyzer/helpers/ui/sqtui/__init__.py
HandsAnalyzer-0.0.6.dist-info/LICENSE
HandsAnalyzer-0.0.6.dist-info/METADATA
HandsAnalyzer-0.0.6.dist-info/WHEEL
HandsAnalyzer-0.0.6.dist-info/top_level.txt
HandsAnalyzer-0.0.6.dist-info/RECORD
